filenamelength/__init__.py
filenamelength/filenamelength.py
filenamelength/locale/es/LC_MESSAGES/filenamelength.mo
filenamelength/locale/es.po
filenamelength/locale/filenamelength.pot
filenamelength/poethepoet.py
filenamelength-1.0.0.dist-info/LICENSE
filenamelength-1.0.0.dist-info/METADATA
filenamelength-1.0.0.dist-info/WHEEL
filenamelength-1.0.0.dist-info/entry_points.txt
filenamelength-1.0.0.dist-info/RECORD
