Metadata-Version: 2.3
Name: filenamelength
Version: 1.0.0
Summary: Admin options to work with the max length of the name of your files
License: GPL-3
Author: turulomio
Author-email: turulomio@yahoo.es
Requires-Python: >=3.9,<4
Classifier: License :: Other/Proprietary License
Classifier: Programming Language :: Python :: 3
Classifier: Programming Language :: Python :: 3.9
Classifier: Programming Language :: Python :: 3.10
Classifier: Programming Language :: Python :: 3.11
Classifier: Programming Language :: Python :: 3.12
Classifier: Programming Language :: Python :: 3.13
Requires-Dist: colorama (>=0.4.6)
Requires-Dist: pydicts (>=1.0.0)
